adafruit_circuitpython_displayio_layout-3.1.2.dist-info/licenses/LICENSE
adafruit_displayio_layout/__init__.py
adafruit_displayio_layout/layouts/__init__.py
adafruit_displayio_layout/layouts/grid_layout.py
adafruit_displayio_layout/layouts/linear_layout.py
adafruit_displayio_layout/layouts/page_layout.py
adafruit_displayio_layout/layouts/tab_layout.py
adafruit_displayio_layout/widgets/__init__.py
adafruit_displayio_layout/widgets/cartesian.py
adafruit_displayio_layout/widgets/control.py
adafruit_displayio_layout/widgets/easing.py
adafruit_displayio_layout/widgets/flip_input.py
adafruit_displayio_layout/widgets/icon_animated.py
adafruit_displayio_layout/widgets/icon_widget.py
adafruit_displayio_layout/widgets/switch_round.py
adafruit_displayio_layout/widgets/widget.py
adafruit_circuitpython_displayio_layout-3.1.2.dist-info/METADATA
adafruit_circuitpython_displayio_layout-3.1.2.dist-info/WHEEL
adafruit_circuitpython_displayio_layout-3.1.2.dist-info/top_level.txt
adafruit_circuitpython_displayio_layout-3.1.2.dist-info/RECORD
