Metadata-Version: 2.4
Name: adafruit-circuitpython-displayio-layout
Version: 3.1.2
Summary: CircuitPython helper library for displayio layouts and widgets.
Author-email: Adafruit Industries <circuitpython@adafruit.com>
License: MIT
Project-URL: Homepage, https://github.com/adafruit/Adafruit_CircuitPython_DisplayIO_Layout
Keywords: adafruit,blinka,circuitpython,micropython,displayio_layout,displayio,gui,layout,widget
Classifier: Intended Audience :: Developers
Classifier: Topic :: Software Development :: Libraries
Classifier: Topic :: Software Development :: Embedded Systems
Classifier: Topic :: System :: Hardware
Classifier: License :: OSI Approved :: MIT License
Classifier: Programming Language :: Python :: 3
License-File: LICENSE
Requires-Dist: Adafruit-Blinka-displayio
Requires-Dist: Adafruit-Blinka
Requires-Dist: adafruit-circuitpython-bitmap-font
Requires-Dist: adafruit-circuitpython-display-text
Requires-Dist: adafruit-circuitpython-imageload
Requires-Dist: adafruit-circuitpython-display-shapes
Requires-Dist: adafruit-circuitpython-typing
Provides-Extra: optional
Dynamic: license-file
